facadedevice/__init__.py
facadedevice/_version.py
facadedevice/device.py
facadedevice/exception.py
facadedevice/graph.py
facadedevice/objects.py
facadedevice/utils.py
facadedevice-1.1.0.dist-info/licenses/LICENSE.txt
facadedevice-1.1.0.dist-info/METADATA
facadedevice-1.1.0.dist-info/WHEEL
facadedevice-1.1.0.dist-info/top_level.txt
facadedevice-1.1.0.dist-info/RECORD
