Metadata-Version: 2.4
Name: facadedevice
Version: 1.1.0
Summary: Provide a descriptive interface for reactive high-level Tango devices.
Author-email: Vincent Michel <vincent.michel@esrf.fr>
Maintainer-email: MAX IV KITS Software <kits-sw@maxiv.lu.se>
License:                     GNU GENERAL PUBLIC LICENSE
Project-URL: Repository, https://gitlab.com/MaxIV/tango-facadedevice
Classifier: Intended Audience :: Developers
Classifier: Topic :: Scientific/Engineering
Classifier: Topic :: Software Development :: Libraries
Classifier: License :: OSI Approved :: GNU General Public License v3 or later (GPLv3+)
Classifier: Programming Language :: Python :: 3
Classifier: Programming Language :: Python :: 3.6
Classifier: Programming Language :: Python :: 3.7
Classifier: Programming Language :: Python :: 3.8
Classifier: Programming Language :: Python :: 3.9
Classifier: Programming Language :: Python :: 3.10
Classifier: Programming Language :: Python :: 3.11
Classifier: Programming Language :: Python :: 3.12
Classifier: Programming Language :: Python :: 3.13
Requires-Python: >=3.6
License-File: LICENSE.txt
Requires-Dist: pytango>=9.2.1
Requires-Dist: numpy>=1.8
Provides-Extra: doc
Requires-Dist: sphinx; extra == "doc"
Requires-Dist: sphinx-rtd-theme; extra == "doc"
Provides-Extra: tests
Requires-Dist: pytest; extra == "tests"
Requires-Dist: pytest-forked; extra == "tests"
Requires-Dist: pytest-cov; extra == "tests"
Dynamic: license-file
